odoo8_addon_stay-8.0.0.1.0-py2.7-nspkg.pth
odoo_addons/stay/stay_demo.xml
odoo_addons/stay/__openerp__.py
odoo_addons/stay/partner.py
odoo_addons/stay/report.xml
odoo_addons/stay/stay_data.xml
odoo_addons/stay/stay.py
odoo_addons/stay/__init__.py
odoo_addons/stay/company.py
odoo_addons/stay/README.rst
odoo_addons/stay/company_view.xml
odoo_addons/stay/stay_view.xml
odoo_addons/stay/partner_view.xml
odoo_addons/stay/security/stay_security.xml
odoo_addons/stay/security/ir.model.access.csv
odoo_addons/stay/report/report_stay_journal.py
odoo_addons/stay/report/report_stay_journal.xml
odoo_addons/stay/report/__init__.py
odoo_addons/stay/i18n/zh_CN.po
odoo_addons/stay/i18n/fr.po
odoo_addons/stay/i18n/stay.pot
odoo_addons/stay/wizard/stay_journal_generate_view.xml
odoo_addons/stay/wizard/stay_journal_print_view.xml
odoo_addons/stay/wizard/__init__.py
odoo_addons/stay/wizard/stay_journal_generate.py
odoo_addons/stay/wizard/stay_journal_print.py
odoo_addons/stay/test/generate_journal.yml
odoo_addons/stay/static/description/icon.png
odoo8_addon_stay-8.0.0.1.0.dist-info/top_level.txt
odoo8_addon_stay-8.0.0.1.0.dist-info/WHEEL
odoo8_addon_stay-8.0.0.1.0.dist-info/RECORD
odoo8_addon_stay-8.0.0.1.0.dist-info/metadata.json
odoo8_addon_stay-8.0.0.1.0.dist-info/DESCRIPTION.rst
odoo8_addon_stay-8.0.0.1.0.dist-info/METADATA
odoo8_addon_stay-8.0.0.1.0.dist-info/namespace_packages.txt
